<?xml version = '1.0' encoding = 'UTF-8'?>
<TableProxySqlServerv2k5 class="oracle.dbtools.crest.model.design.storage.sqlserver.v2k5.TableProxySqlServerv2k5" name="SensorEvent" directorySegmentName="seg_0" id="1E2BB017-FAE9-B741-B025-CD1CBE1575FC">
<createdBy>marky</createdBy>
<createdTime>2026-03-15 20:09:05 UTC</createdTime>
<ownerDesignName>ERD</ownerDesignName>
<database>DB_NULLELEMENT</database>
<columnProxies>
<ColumnProxy class="oracle.dbtools.crest.model.design.storage.sqlserver.v2k12.ColumnProxySqlServerv2k12" name="eventTime" id="40794031-924A-B3DA-506C-2CFC90C923E5">
<createdBy>marky</createdBy>
<createdTime>2026-03-15 20:09:05 UTC</createdTime>
<ownerDesignName>ERD</ownerDesignName>
</ColumnProxy>
<ColumnProxy class="oracle.dbtools.crest.model.design.storage.sqlserver.v2k12.ColumnProxySqlServerv2k12" name="sensorId" id="6BA51A4B-DB12-B06D-43B4-8A1276BDA5F1">
<createdBy>marky</createdBy>
<createdTime>2026-03-15 20:09:05 UTC</createdTime>
<ownerDesignName>ERD</ownerDesignName>
</ColumnProxy>
<ColumnProxy class="oracle.dbtools.crest.model.design.storage.sqlserver.v2k12.ColumnProxySqlServerv2k12" name="eventType" id="C28150B2-9916-97BB-632D-19BE005424A5">
<createdBy>marky</createdBy>
<createdTime>2026-03-15 20:09:05 UTC</createdTime>
<ownerDesignName>ERD</ownerDesignName>
</ColumnProxy>
<ColumnProxy class="oracle.dbtools.crest.model.design.storage.sqlserver.v2k12.ColumnProxySqlServerv2k12" name="id" id="CC1473CA-033C-BC5A-25E9-2224249D530E">
<createdBy>marky</createdBy>
<createdTime>2026-03-15 20:09:05 UTC</createdTime>
<ownerDesignName>ERD</ownerDesignName>
</ColumnProxy>
</columnProxies>
<foreignKeys>
<ForeignKey class="oracle.dbtools.crest.model.design.storage.sqlserver.v2k5.FKProxySqlServerv2k5" name="FK_ASS_1" id="01F5BF98-7495-C9EE-F300-170E17BC9052">
<createdBy>marky</createdBy>
<createdTime>2026-03-15 20:09:05 UTC</createdTime>
<ownerDesignName>ERD</ownerDesignName>
</ForeignKey>
</foreignKeys>
<primaryKeys>
<PrimaryKey class="oracle.dbtools.crest.model.design.storage.sqlserver.v2k5.PKProxySqlServerv2k5" name="SensorEvent__IDX" id="00D62B72-B5E0-6FCE-C2CF-6918EDB7CA00">
<createdBy>marky</createdBy>
<createdTime>2026-03-15 20:09:05 UTC</createdTime>
<ownerDesignName>ERD</ownerDesignName>
<clustered>true</clustered>
</PrimaryKey>
</primaryKeys>
</TableProxySqlServerv2k5>